jupyter_wren_syntax/__init__.py
jupyter_wren_syntax/_version.py
jupyter_wren_syntax/labextension/build_log.json
jupyter_wren_syntax/labextension/package.json
jupyter_wren_syntax/labextension/static/lib_index_js.257e7af93ee618f7d9c5.js
jupyter_wren_syntax/labextension/static/lib_index_js.257e7af93ee618f7d9c5.js.map
jupyter_wren_syntax/labextension/static/remoteEntry.a7ffe26201ed2eee8505.js
jupyter_wren_syntax/labextension/static/remoteEntry.a7ffe26201ed2eee8505.js.map
jupyter_wren_syntax/labextension/static/style.js
jupyter_wren_syntax/labextension/static/style_index_js.fb500f3f922c572e6678.js
jupyter_wren_syntax/labextension/static/style_index_js.fb500f3f922c572e6678.js.map
jupyter_wren_syntax/labextension/static/vendors-node_modules_css-loader_dist_runtime_api_js-node_modules_css-loader_dist_runtime_cssW-926fd9.47a3d780f1bd30874b71.js
jupyter_wren_syntax/labextension/static/vendors-node_modules_css-loader_dist_runtime_api_js-node_modules_css-loader_dist_runtime_cssW-926fd9.47a3d780f1bd30874b71.js.map
jupyter_wren_syntax-0.1.1.data/data/share/jupyter/labextensions/jupyter-wren-syntax/build_log.json
jupyter_wren_syntax-0.1.1.data/data/share/jupyter/labextensions/jupyter-wren-syntax/install.json
jupyter_wren_syntax-0.1.1.data/data/share/jupyter/labextensions/jupyter-wren-syntax/package.json
jupyter_wren_syntax-0.1.1.data/data/share/jupyter/labextensions/jupyter-wren-syntax/static/lib_index_js.257e7af93ee618f7d9c5.js
jupyter_wren_syntax-0.1.1.data/data/share/jupyter/labextensions/jupyter-wren-syntax/static/lib_index_js.257e7af93ee618f7d9c5.js.map
jupyter_wren_syntax-0.1.1.data/data/share/jupyter/labextensions/jupyter-wren-syntax/static/remoteEntry.a7ffe26201ed2eee8505.js
jupyter_wren_syntax-0.1.1.data/data/share/jupyter/labextensions/jupyter-wren-syntax/static/remoteEntry.a7ffe26201ed2eee8505.js.map
jupyter_wren_syntax-0.1.1.data/data/share/jupyter/labextensions/jupyter-wren-syntax/static/style.js
jupyter_wren_syntax-0.1.1.dist-info/LICENSE
jupyter_wren_syntax-0.1.1.dist-info/METADATA
jupyter_wren_syntax-0.1.1.dist-info/WHEEL
jupyter_wren_syntax-0.1.1.dist-info/top_level.txt
jupyter_wren_syntax-0.1.1.dist-info/RECORD
